{
  "db_name": "PostgreSQL",
  "query": "\n        SELECT id, username, password, role as \"role: UserRole\" FROM users WHERE id = $1\n        ",
  "describe": {
    "columns": [
      {
        "ordinal": 0,
        "name": "id",
        "type_info": "Int4"
      },
      {
        "ordinal": 1,
        "name": "username",
        "type_info": "Varchar"
      },
      {
        "ordinal": 2,
        "name": "password",
        "type_info": "Varchar"
      },
      {
        "ordinal": 3,
        "name": "role: UserRole",
        "type_info": {
          "Custom": {
            "name": "user_role",
            "kind": {
              "Enum": [
                "basic",
                "admin"
              ]
            }
          }
        }
      }
    ],
    "parameters": {
      "Left": [
        "Int4"
      ]
    },
    "nullable": [
      false,
      false,
      false,
      false
    ]
  },
  "hash": "1de9955b63c687976d41f79596c0bae30cf2748678be1cf4a2b0df0ea96f9648"
}
